{"cameraMode":{"drawMode":0,"name":"Shaded","section":"Shading Mode"},"sceneLighting":true,"audioPlay":false,"sceneViewState":{"m_AlwaysRefresh":false,"showFog":true,"showSkybox":true,"showFlares":true,"showImageEffects":true,"showParticleSystems":true,"showVisualEffectGraphs":true,"m_FxEnabled":true},"in2DMode":false,"pivot":{"x":-3.6008758544921877,"y":11.140213012695313,"z":-117.97528839111328},"rotation":{"x":0.030642027035355569,"y":-0.9338844418525696,"z":-0.04434569925069809,"w":-0.3558083176612854},"size":44.119102478027347,"orthographic":false}